pttechnologies/__init__.py
pttechnologies/_version.py
pttechnologies/pttechnologies.py
pttechnologies/definitions/__init__.py
pttechnologies/definitions/admin.json
pttechnologies/definitions/cook.json
pttechnologies/definitions/cook_from_wappalyzer.json
pttechnologies/definitions/cooklen.json
pttechnologies/definitions/defpage.json
pttechnologies/definitions/docs.json
pttechnologies/definitions/errpage.json
pttechnologies/definitions/hdrval.json
pttechnologies/definitions/hdrval_from_wappalyzer.json
pttechnologies/definitions/jslib.json
pttechnologies/definitions/meta.json
pttechnologies/definitions/meta_from_wappalyzer.json
pttechnologies/definitions/pllng.json
pttechnologies/definitions/plugins.json
pttechnologies/definitions/predict.json
pttechnologies/definitions/predict_from_wappalyzer.json
pttechnologies/definitions/proto.json
pttechnologies/definitions/sources.json
pttechnologies/definitions/wsrho.json
pttechnologies/definitions/wsurllen.json
pttechnologies/definitions/products/_.json
pttechnologies/definitions/products/a.json
pttechnologies/definitions/products/b.json
pttechnologies/definitions/products/c.json
pttechnologies/definitions/products/categories.json
pttechnologies/definitions/products/d.json
pttechnologies/definitions/products/e.json
pttechnologies/definitions/products/f.json
pttechnologies/definitions/products/g.json
pttechnologies/definitions/products/h.json
pttechnologies/definitions/products/i.json
pttechnologies/definitions/products/j.json
pttechnologies/definitions/products/k.json
pttechnologies/definitions/products/l.json
pttechnologies/definitions/products/m.json
pttechnologies/definitions/products/n.json
pttechnologies/definitions/products/o.json
pttechnologies/definitions/products/p.json
pttechnologies/definitions/products/q.json
pttechnologies/definitions/products/r.json
pttechnologies/definitions/products/s.json
pttechnologies/definitions/products/t.json
pttechnologies/definitions/products/u.json
pttechnologies-0.0.34.dist-info/licenses/LICENSE
pttechnologies-0.0.34.dist-info/METADATA
pttechnologies-0.0.34.dist-info/WHEEL
pttechnologies-0.0.34.dist-info/entry_points.txt
pttechnologies-0.0.34.dist-info/top_level.txt
pttechnologies-0.0.34.dist-info/RECORD
